{
  "id": "221132",
  "forum_id": "39",
  "title": "WTB: Cicotte & Wagner (bat on left) Piedmont 150",
  "author": "VintageJay",
  "reply_count": 1,
  "view_count": 173,
  "created_date": null,
  "last_reply": "20160416T13:23:54-06:00",
  "posts": [
    {
      "post_id": "1528208",
      "post_title": "WTB: Cicotte & Wagner (bat on left) Piedmont 150",
      "post_author_name": "VintageJay",
      "post_content": "I'm looking to buy T206 Ed Cicotte and Heinie Wagner (bat on left shoulder) Piedmont 150 cards.\r\n\r\nI prefer raw. Any condition will do!\r\n\r\nThanks,\r\nJay",
      "post_time": "20160416T03:15:47-06:00",
      "timestamp": "1460798147"
    },
    {
      "post_id": "1528351",
      "post_title": "",
      "post_author_name": "xplainer",
      "post_content": "Here is one I have on eBay.\r\nLet me know if interested. Maybe we can work out a deal - through here - and complete on eBay.\r\n\r\n[url]http://www.ebay.com/itm/172148787012?ssPageName=STRK:MESELX:IT&_trksid=p3984.m1555.l2649[/url]\r\n\r\n-Jimmy",
      "post_time": "20160416T13:23:54-06:00",
      "timestamp": "1460834634"
    }
  ]
}