{
  "id": "220809",
  "forum_id": "39",
  "title": "T206 Blank Back",
  "author": "usernamealreadytaken",
  "reply_count": 1,
  "view_count": 291,
  "created_date": null,
  "last_reply": "20160409T08:05:29-06:00",
  "posts": [
    {
      "post_id": "1525274",
      "post_title": "T206 Blank Back",
      "post_author_name": "usernamealreadytaken",
      "post_content": "Looking to trade for a Red Hindu. Let me know if interested. Thanks! Chris.",
      "post_time": "20160409T08:04:26-06:00",
      "timestamp": "1460210666"
    },
    {
      "post_id": "1525275",
      "post_title": "Pic",
      "post_author_name": "usernamealreadytaken",
      "post_content": "Front",
      "post_time": "20160409T08:05:29-06:00",
      "timestamp": "1460210729"
    }
  ]
}