{
  "id": "294041",
  "forum_id": "39",
  "title": "FS: Mathewson: dark cap SOLD",
  "author": "Michael Peich",
  "reply_count": 0,
  "view_count": 364,
  "created_date": null,
  "last_reply": "20201229T13:47:01-06:00",
  "posts": [
    {
      "post_id": "2050815",
      "post_title": "FS: Mathewson: dark cap SOLD",
      "post_author_name": "Michael Peich",
      "post_content": "Offered is Mathewson: dark cap\r\n\r\n[STRIKE]$575.00[/STRIKE]     SOLD\r\n\r\n\"I'll take it\" supersedes any negotiations\r\n\r\nShipping: $5.00\r\n\r\nPayment by PP f/f: [url]mpeich12@gmail.com[/url]\r\n\r\nIf you are interested, or have questions, please email: [url]mpeich12@gmail.com[/url]. No PMs, please. \r\n\r\nThank you for looking!\r\n\r\nCheers,\r\nMike",
      "post_time": "20201229T13:47:01-06:00",
      "timestamp": "1609274821"
    }
  ]
}