{
  "id": "193662",
  "forum_id": "39",
  "title": "Heinie & the 3 Bears",
  "author": "Jantz",
  "reply_count": 0,
  "view_count": 242,
  "created_date": null,
  "last_reply": "20140908T15:47:54-06:00",
  "posts": [
    {
      "post_id": "1319872",
      "post_title": "Heinie & the 3 Bears",
      "post_author_name": "Jantz",
      "post_content": "I have four T206s for sale/trade. Will consider trades for other T206s (about the same condition) that I need for my set.\r\n\r\nCheck / Postal M.O. / Paypal are fine as payment.\r\n\r\nUnglaub  SGC 30  Polar Bear (faint wrinkle in right upper corner)  $34\r\n\r\nStahl (glove shows)  SGC 30  Polar Bear (multiple creases & wrinkles)  $30\r\n\r\nBerger SGC 40  Polar Bear  (small crease near left lower corner)  $42\r\n\r\nMiller  SGC 40  Sweet Cap. 350 f#30 ( no creases or wrinkles)  $42 \r\n\r\n\r\nPost or PM me.\r\n\r\nThanks\r\n\r\nJantz",
      "post_time": "20140908T15:47:54-06:00",
      "timestamp": "1410212874"
    }
  ]
}