{
  "id": "346282",
  "forum_id": "39",
  "title": "LTB Mathewson/WaJo T206 Piedmont 42",
  "author": "cliffyb",
  "reply_count": 2,
  "view_count": 335,
  "created_date": null,
  "last_reply": "20240303T19:05:57-06:00",
  "posts": [
    {
      "post_id": "2412548",
      "post_title": "LTB Mathewson/WaJo T206 Piedmont 42",
      "post_author_name": "cliffyb",
      "post_content": "Taking a long shot here. I'm interested in buying a T206 Mathewson or WaJo Piedmont 350-460/42. If interested please send me a PM. Thanks much.",
      "post_time": "20240213T12:20:54-06:00",
      "timestamp": "1707852054"
    },
    {
      "post_id": "2412668",
      "post_title": "P42",
      "post_author_name": "helfrich91",
      "post_content": "PM sent",
      "post_time": "20240213T17:07:30-06:00",
      "timestamp": "1707869250"
    },
    {
      "post_id": "2417089",
      "post_title": "",
      "post_author_name": "cliffyb",
      "post_content": "Bump",
      "post_time": "20240303T19:05:57-06:00",
      "timestamp": "1709517957"
    }
  ]
}