{
  "id": "230285",
  "forum_id": "39",
  "title": "Polar Bear, Sweet Cap and Piedmont Back Graded and Ungraded",
  "author": "rocarroll",
  "reply_count": 1,
  "view_count": 461,
  "created_date": null,
  "last_reply": "20161023T12:21:07-06:00",
  "posts": [
    {
      "post_id": "1596152",
      "post_title": "Polar Bear, Sweet Cap and Piedmont Back Graded and Ungraded",
      "post_author_name": "rocarroll",
      "post_content": "Up for Grabs is a:\n\nIrv Young ungraded/unaltered.  Gorgeous card with no creases and very strong corners.  Should grade at least a 4.  SOLD\n\nGeorge Merritt Polar Bear SGC 30  SOLD\n\nGeorge Stone Sweet Cap SGC 40 SOLD\n\nPrice includes shipping.  Paypal F/F.",
      "post_time": "20161023T12:08:11-06:00",
      "timestamp": "1477246091"
    },
    {
      "post_id": "1596157",
      "post_title": "",
      "post_author_name": "Beatles Guy",
      "post_content": "Hi Ryan.  I'll take Irv.",
      "post_time": "20161023T12:21:07-06:00",
      "timestamp": "1477246867"
    }
  ]
}