{
  "id": "204852",
  "forum_id": "39",
  "title": "Wanted: Green Cobb Old Mill",
  "author": "bundy462",
  "reply_count": 1,
  "view_count": 235,
  "created_date": null,
  "last_reply": "20150501T00:35:19-06:00",
  "posts": [
    {
      "post_id": "1404153",
      "post_title": "Wanted: Green Cobb Old Mill",
      "post_author_name": "bundy462",
      "post_content": "Anyone out there have a green Cobb with an Old Mill back that they'd consider moving? I would like to purchase or trade (or combo). I have various Matty, WaJo, Cobb, and Lajoie cards that I can trade.\r\n\r\nThanks.",
      "post_time": "20150422T16:37:32-06:00",
      "timestamp": "1429742252"
    },
    {
      "post_id": "1406901",
      "post_title": "bump",
      "post_author_name": "bundy462",
      "post_content": "bump",
      "post_time": "20150501T00:35:19-06:00",
      "timestamp": "1430462119"
    }
  ]
}