{
  "id": "176271",
  "forum_id": "39",
  "title": "HOF T 206's For sale",
  "author": "flash300",
  "reply_count": 0,
  "view_count": 273,
  "created_date": null,
  "last_reply": "20130924T20:47:48-06:00",
  "posts": [
    {
      "post_id": "1188611",
      "post_title": "HOF T 206's For sale",
      "post_author_name": "flash300",
      "post_content": "Chief Bender portrait Ped 150                     PSA 3      $ 174 dlv\r\nIron Man Mcginnity    Sweet cap 350           PSA 3.5   $ 174 dlv\r\nJohn McGraw Sweet Cap 350 460                PSA 2     $ 134 dlv\r\nHughie Jennings Sweet Cap 350 460 fac 42   PSA 4     $ 259 dlv\r\nNap Lajoie Ped 150                                   PSA 4     $ 599 dlv \r\nChief Bender w/Trees ped 350                    PSA 3     $ 174 dlv\r\nJoe Kelley Sweet Cap 350                          PSA 3     Sold\r\nFrank Chance yellow portrait Sweet Cap 350 PSA 3.5  $ 239 dlv \r\n\r\n\r\nPayment via Paypal or Money Order Check out my Ebay Store for other T's \r\nBigskysc \r\n\r\n\r\n\r\n[url]http://s261.photobucket.com/user/philsbucket/library/GRADED%20T%20206?sort=6&page=1[/url]",
      "post_time": "20130924T20:47:48-06:00",
      "timestamp": "1380077268"
    }
  ]
}