{
  "id": "213550",
  "forum_id": "39",
  "title": "FS:  Hindu Ed Walsh - SGC 10 - $old",
  "author": "t206fix",
  "reply_count": 0,
  "view_count": 268,
  "created_date": null,
  "last_reply": "20151102T11:06:44-06:00",
  "posts": [
    {
      "post_id": "1467919",
      "post_title": "FS:  Hindu Ed Walsh - SGC 10 - $old",
      "post_author_name": "t206fix",
      "post_content": "FS:  Hindu Ed Walsh - SGC 10 - $old\r\n\r\npaypal gift or add 3%",
      "post_time": "20151102T11:06:44-06:00",
      "timestamp": "1446487604"
    }
  ]
}