{
  "id": "214027",
  "forum_id": "39",
  "title": "WTB Cy young Portrait FOUND on to cobb",
  "author": "CrazyDiamond",
  "reply_count": 1,
  "view_count": 302,
  "created_date": null,
  "last_reply": "20151115T10:43:02-06:00",
  "posts": [
    {
      "post_id": "1471951",
      "post_title": "WTB Cy young Portrait FOUND on to cobb",
      "post_author_name": "CrazyDiamond",
      "post_content": "Looking for a Cy young portrait PSA/SGC 1-2 range with nice eye appeal\r\n\r\nPlease PM me if you have anything for sale\r\n\r\nThanks",
      "post_time": "20151112T13:17:00-06:00",
      "timestamp": "1447359420"
    },
    {
      "post_id": "1472959",
      "post_title": "",
      "post_author_name": "CrazyDiamond",
      "post_content": "Found one Thanks!\r\n\r\nSettled on a raw example\r\n\r\nnow looking for cobb bat off \r\n\r\nPSA/SGC graded 1-2 nice eye appeal\r\n\r\nwould consider raw equivalents\r\n\r\nPlease PM me what you have\r\n\r\nThanks",
      "post_time": "20151115T10:43:02-06:00",
      "timestamp": "1447609382"
    }
  ]
}