{
  "id": "322462",
  "forum_id": "4",
  "title": "**SOLD**Beautiful Abner Doubleday original engraving stunning",
  "author": "JMANOS",
  "reply_count": 4,
  "view_count": 470,
  "created_date": null,
  "last_reply": "20220724T19:00:58-06:00",
  "posts": [
    {
      "post_id": "2244588",
      "post_title": "**SOLD**Beautiful Abner Doubleday original engraving stunning",
      "post_author_name": "JMANOS",
      "post_content": "email me for scans [url]jmanos6@att.net[/url] $400 by Brady",
      "post_time": "20220721T10:21:56-06:00",
      "timestamp": "1658420516"
    },
    {
      "post_id": "2245107",
      "post_title": "",
      "post_author_name": "benge610",
      "post_content": "Just curious,\n\"engraving\" or \"CDV\" by Brady?\n(for clarification)\nCuz, an engraving by Brady, wow. gotta see.\n[url]bengehler5@gmail.com[/url]\nBen\n\n\"I love baseball history backstory; especially when it involves cards.\"",
      "post_time": "20220723T07:53:15-06:00",
      "timestamp": "1658584395"
    },
    {
      "post_id": "2245126",
      "post_title": "",
      "post_author_name": "mrreality68",
      "post_content": "just curios any way you can post pictures. You seem to have some really interesting items that i or others may be interested in but no pictures makes it hard then we need to email you etc",
      "post_time": "20220723T09:23:05-06:00",
      "timestamp": "1658589785"
    },
    {
      "post_id": "2245142",
      "post_title": "",
      "post_author_name": "benge610",
      "post_content": "[quote name=\"benge610\" post=2245107]Just curious,\n\"engraving\" or \"CDV\" by Brady?\n(for clarification)\nCuz, an engraving by Brady, wow. gotta see.\n[url]bengehler5@gmail.com[/url]\nBen\n\n\"I love baseball history backstory; especially when it involves cards.\"[/QUOTE]\n\nWow. Engraving, yes.\nStunning, YES.",
      "post_time": "20220723T10:18:16-06:00",
      "timestamp": "1658593096"
    },
    {
      "post_id": "2245542",
      "post_title": "how about $300",
      "post_author_name": "JMANOS",
      "post_content": "$300 email me for scans [url]jmanos6@att.net[/url]",
      "post_time": "20220724T19:00:58-06:00",
      "timestamp": "1658710858"
    }
  ]
}