{
  "id": "197091",
  "forum_id": "4",
  "title": "N43 Ewing FS or looking to trade AVAILABLE",
  "author": "JasonD08",
  "reply_count": 5,
  "view_count": 591,
  "created_date": null,
  "last_reply": "20150306T07:52:00-06:00",
  "posts": [
    {
      "post_id": "1345613",
      "post_title": "N43 Ewing FS or looking to trade AVAILABLE",
      "post_author_name": "JasonD08",
      "post_content": "Looking for cash, T Cobbs, 1930s Ruth, or Aaron or Clemente Rookies.  Open for any other graded pre-war HOFers. Also Mark is on the holder or scanner, not the card.\n\n\n\nThanks\n\nJason",
      "post_time": "20141118T07:34:28-06:00",
      "timestamp": "1416321268"
    },
    {
      "post_id": "1349172",
      "post_title": "",
      "post_author_name": "JasonD08",
      "post_content": "BUMP would consider trade not his one.",
      "post_time": "20141129T07:18:21-06:00",
      "timestamp": "1417270701"
    },
    {
      "post_id": "1387399",
      "post_title": "",
      "post_author_name": "JasonD08",
      "post_content": "Bump",
      "post_time": "20150305T11:34:45-06:00",
      "timestamp": "1425580485"
    },
    {
      "post_id": "1387603",
      "post_title": "",
      "post_author_name": "jcmtiger",
      "post_content": "Where is the scan or picture?\n\nJoe",
      "post_time": "20150305T22:26:15-06:00",
      "timestamp": "1425619575"
    },
    {
      "post_id": "1387626",
      "post_title": "",
      "post_author_name": "ullmandds",
      "post_content": "only dogs can see it!:D",
      "post_time": "20150306T05:03:39-06:00",
      "timestamp": "1425643419"
    },
    {
      "post_id": "1387652",
      "post_title": "",
      "post_author_name": "JasonD08",
      "post_content": "My bad guys.  I thought I had a link.  I will post a scan later today.\n\nJason",
      "post_time": "20150306T07:52:00-06:00",
      "timestamp": "1425653520"
    }
  ]
}