{
  "id": "251109",
  "forum_id": "4",
  "title": "FS: 1920\u2019s Victoriaville Quebec College Team Postcard",
  "author": "baseball tourist",
  "reply_count": 1,
  "view_count": 265,
  "created_date": null,
  "last_reply": "20180213T10:26:35-06:00",
  "posts": [
    {
      "post_id": "1746694",
      "post_title": "FS: 1920\u2019s Victoriaville Quebec College Team Postcard",
      "post_author_name": "baseball tourist",
      "post_content": "Asking $20 shipped. Please ask any questions you have. Thanks for looking! Chris",
      "post_time": "20180209T20:00:57-06:00",
      "timestamp": "1518231657"
    },
    {
      "post_id": "1747667",
      "post_title": "Price drop",
      "post_author_name": "baseball tourist",
      "post_content": "Dropped to $20 shipped",
      "post_time": "20180213T10:26:35-06:00",
      "timestamp": "1518542795"
    }
  ]
}