{
  "id": "247502",
  "forum_id": "4",
  "title": "Ty Cobb dietsche postcard for sale - Traded",
  "author": "bigfish",
  "reply_count": 0,
  "view_count": 310,
  "created_date": null,
  "last_reply": "20171113T07:41:15-06:00",
  "posts": [
    {
      "post_id": "1719537",
      "post_title": "Ty Cobb dietsche postcard for sale - Traded",
      "post_author_name": "bigfish",
      "post_content": "Traded",
      "post_time": "20171113T07:41:15-06:00",
      "timestamp": "1510584075"
    }
  ]
}