{
  "id": "68463",
  "forum_id": "4",
  "title": "WANTED 1887 N172 OLD JUDGE PUD GALVIN",
  "author": "Archive",
  "reply_count": 2,
  "view_count": 810,
  "created_date": null,
  "last_reply": "20071220T23:02:00-06:00",
  "posts": [
    {
      "post_id": "373196",
      "post_title": "WANTED 1887 N172 OLD JUDGE PUD GALVIN",
      "post_author_name": "Archive",
      "post_content": "Posted By: TONY GARCIA III\nI am looking for an 1887 Old Judge N172 Pud Galvin. Please e-mail me if you are interested in selling. Thanks.",
      "post_time": "20071220T17:04:00-06:00",
      "timestamp": "1198195440"
    },
    {
      "post_id": "373197",
      "post_title": "WANTED 1887 N172 OLD JUDGE PUD GALVIN",
      "post_author_name": "Archive",
      "post_content": "Posted By: barrysloate\nHi Tony- In my upcoming January auction I have a Galvin SGC 30 with a nice photo. Catalog will be mailed in a couple of weeks. Regards, Barry",
      "post_time": "20071220T17:13:00-06:00",
      "timestamp": "1198195980"
    },
    {
      "post_id": "373198",
      "post_title": "WANTED 1887 N172 OLD JUDGE PUD GALVIN",
      "post_author_name": "Archive",
      "post_content": "Posted By: TONY GARCIA III\nThanks for the heads up Barry. I have bought some items from you in the past and your auctions are awesome. Thanks.",
      "post_time": "20071220T23:02:00-06:00",
      "timestamp": "1198216920"
    }
  ]
}