{
  "id": "68480",
  "forum_id": "4",
  "title": "Forsale 1906 White Sox Team PC postally unused",
  "author": "Archive",
  "reply_count": 0,
  "view_count": 530,
  "created_date": null,
  "last_reply": "20080109T15:33:00-06:00",
  "posts": [
    {
      "post_id": "373243",
      "post_title": "Forsale 1906 White Sox Team PC postally unused",
      "post_author_name": "Archive",
      "post_content": "Posted By: Jim Manos\nNeat piece original postcard and a little larger than the normal pc. This is 6 1/2 x 5  copyright by (looks like) Frech, Wagner. Also back say's Mailing Card not postcard (maybe that is why it is larger?? Don't know) $450 Right edge seems to be trimmed.  Feel frre to make a offer. went to ebay",
      "post_time": "20080109T15:33:00-06:00",
      "timestamp": "1199917980"
    }
  ]
}