{
  "id": "233545",
  "forum_id": "4",
  "title": "N332 SF Hess wantlist",
  "author": "epike3",
  "reply_count": 5,
  "view_count": 1317,
  "created_date": null,
  "last_reply": "20170904T07:24:44-06:00",
  "posts": [
    {
      "post_id": "1618255",
      "post_title": "N332 SF Hess wantlist",
      "post_author_name": "epike3",
      "post_content": "Looking to pick up an N332 SF Hess track and field athlete.\n\nThese are the ones that I am aware of - if you have seen any other, please LMK and interested in pictures even if I cannot get the original: \n\n WM Cummins, George Cartwright, Malcolm Ford\n\nPlease send a PM and/or email ehpiiiATaolDOTcom.\n\nThanks!\n\nBest,\nEd",
      "post_time": "20170107T22:43:55-06:00",
      "timestamp": "1483854235"
    },
    {
      "post_id": "1639470",
      "post_title": "still looking!",
      "post_author_name": "epike3",
      "post_content": "bump",
      "post_time": "20170309T21:28:50-06:00",
      "timestamp": "1489120130"
    },
    {
      "post_id": "1639605",
      "post_title": "",
      "post_author_name": "Fred",
      "post_content": "Ed, you have an actual want list for that series?  I just want one... that would be my want list....  good luck!",
      "post_time": "20170310T10:56:54-06:00",
      "timestamp": "1489168614"
    },
    {
      "post_id": "1639652",
      "post_title": "",
      "post_author_name": "sthoemke",
      "post_content": "I have a Malcolm Ford, if I can locate it.",
      "post_time": "20170310T13:32:09-06:00",
      "timestamp": "1489177929"
    },
    {
      "post_id": "1676670",
      "post_title": "still looking!",
      "post_author_name": "epike3",
      "post_content": "bump",
      "post_time": "20170702T08:06:56-06:00",
      "timestamp": "1499004416"
    },
    {
      "post_id": "1697692",
      "post_title": "still looking!",
      "post_author_name": "epike3",
      "post_content": "bump",
      "post_time": "20170904T07:24:44-06:00",
      "timestamp": "1504531484"
    }
  ]
}