{
  "id": "68653",
  "forum_id": "4",
  "title": "WTB Cap Anson N300, N28, N172",
  "author": "Archive",
  "reply_count": 1,
  "view_count": 521,
  "created_date": null,
  "last_reply": "20080702T12:14:00-06:00",
  "posts": [
    {
      "post_id": "373728",
      "post_title": "WTB Cap Anson N300, N28, N172",
      "post_author_name": "Archive",
      "post_content": "Posted By: Jamie\nanyone have any of these thre cards in low grade for sale emial me thanks",
      "post_time": "20080702T11:50:00-06:00",
      "timestamp": "1215021000"
    },
    {
      "post_id": "373729",
      "post_title": "WTB Cap Anson N300, N28, N172",
      "post_author_name": "Archive",
      "post_content": "Posted By: bigfish\nI have one.  E-mail me if interested\n\ntp7161@yahoo.com",
      "post_time": "20080702T12:14:00-06:00",
      "timestamp": "1215022440"
    }
  ]
}