{
  "id": "147621",
  "forum_id": "13",
  "title": "WTB:  T206 Addie Joss Pitching",
  "author": "Tyler",
  "reply_count": 1,
  "view_count": 451,
  "created_date": null,
  "last_reply": "20120220T08:44:45-06:00",
  "posts": [
    {
      "post_id": "967052",
      "post_title": "WTB:  T206 Addie Joss Pitching",
      "post_author_name": "Tyler",
      "post_content": "I am looking for a presentable T206 Addie Joss pitching pose, either raw or graded 1-2 range.  \n\nOpen to any of the various backs.\n\nPlease email me if you are looking to sell.\n\nThanks,\nTyler\n\n[url]tilercox@aol.com[/url]",
      "post_time": "20120214T11:13:24-06:00",
      "timestamp": "1329243204"
    },
    {
      "post_id": "968709",
      "post_title": "Bump",
      "post_author_name": "Tyler",
      "post_content": "I am still interested in other backs for this card.  Other than Tolstoi or Polar Bear.\n\nMajor thanks to David L. for a great deal.  He sold me the card for less than my offer...then shipped same day with delivery confirmation.  True gentleman.\n\nLet me know if there are any other low grade Joss pitching pose out there for sale.\n\nThanks,\n\nTyler",
      "post_time": "20120220T08:44:45-06:00",
      "timestamp": "1329752685"
    }
  ]
}