{
  "id": "134057",
  "forum_id": "13",
  "title": "FS: 3 T206 Southern League Players",
  "author": "lharri3600",
  "reply_count": 0,
  "view_count": 255,
  "created_date": null,
  "last_reply": "20110306T18:01:37-06:00",
  "posts": [
    {
      "post_id": "876489",
      "post_title": "FS: 3 T206 Southern League Players",
      "post_author_name": "lharri3600",
      "post_content": "Selling the following 3 T206 Southern League Players:",
      "post_time": "20110306T18:01:37-06:00",
      "timestamp": "1299459697"
    }
  ]
}