{
  "id": "197031",
  "forum_id": "13",
  "title": "wtb: T202s",
  "author": "1952boyntoncollector",
  "reply_count": 1,
  "view_count": 253,
  "created_date": null,
  "last_reply": "20141117T13:08:37-06:00",
  "posts": [
    {
      "post_id": "1345134",
      "post_title": "wtb: T202s",
      "post_author_name": "1952boyntoncollector",
      "post_content": "psa 5 or better or equivalent..",
      "post_time": "20141116T18:13:19-06:00",
      "timestamp": "1416186799"
    },
    {
      "post_id": "1345341",
      "post_title": "",
      "post_author_name": "Peter_Spaeth",
      "post_content": "PSA 5 Speaker/Wood?  :D:D",
      "post_time": "20141117T13:08:37-06:00",
      "timestamp": "1416254917"
    }
  ]
}