{
  "id": "97557",
  "forum_id": "13",
  "title": "Forty T-206 Phillies for Sale (incl. scarce backs)",
  "author": "Archive",
  "reply_count": 0,
  "view_count": 245,
  "created_date": null,
  "last_reply": "20080330T08:29:00-06:00",
  "posts": [
    {
      "post_id": "681183",
      "post_title": "Forty T-206 Phillies for Sale (incl. scarce backs)",
      "post_author_name": "Archive",
      "post_content": "Posted By: Marc S.\nLooking to sell as a group.  Scans of all card available upon request.  Looking for $1,895 - or best offer.\n\n\nKitty Bransfield PSA 4 VG/EX Piedmont 350\n\nKitty Bransfield PSA 4 VG/EX Piedmont 150\n\nKitty Bransfield PSA 4 VG/EX Sweet Cap 150, Factory 649 Overprint\n\nHarry Covaleski PSA 5 Excellent Old Mill\n\nHarry Covaleski SGC 40 Very Good  EPDG\n\nHarry Covaleski PSA 1 Poor-Fair Sovereign 150\n\nHarry Covaleski PSA 5 Excellent Sweet Cap 350, Factory 25\n\nRed Dooin PSA 2 Good EPDG\n\nRed Dooin PSA 4 VG/EX Piedmont 350\n\nRed Dooin PSA 3 Very Good Sweet Cap 150\n\nRed Dooin PSA 4 VG/EX Piedmont 150\n\nMickey Doolan Batting PSA 2 Good Sweet Cap 350/460, Factory 42 OP\n\nMickey Doolan Fielding PSA 4 VG/EX Sweet Cap 350, Factory 25\n\nMickey Doolin Portrait PSA 3 Very Good Sweet Cap 350, Factory 30\n\nMickey Doolin Portrait PSA 4 VG / EX Sweet Cap 350, Factory 25\n\nMickey Doolin Portrait PSA 3 Very Good Piedmont 350\n\nMickey Doolin Portrait PSA 4 VG/EX Sovereign 150\n\nMickey Doolin Portrait PSA 4 VG/EX Piedmont 150\n\nFred Jacklitsch PSA 4 VG/EX Piedmont 350\n\nFred Jacklitsch PSA 3 Very Good Sweet Cap 150\n\nFred Jacklitsch SGC 40 Very Good Old Mill\n\nFred Jacklitsch PSA 5 Excellent Sweet Cap 350 Factory 30\n\nOtto Knabe PSA 4 VG/Ex Sweet Cap 350 Factory 30\n\nOtto Knabe PSA 5 Excellent Sovereign 350\n\nOtto Knabe PSA 4 VG/Ex Sweet Cap 350 Factory 25\n\nSherry Magee Portrait PSA 1 Poor-Fair Sovereign 150 (great eye appeal, tape stain on back)\n\nSherry Magee Portrait SGC 40 Very Good Piedmont 350\n\nSherry Magee with Bat PSA 4 VG/EX Sweet Cap 350/460, Factory 42 OP\n\nGeorge McQuillan Ball in Hand PSA 4 VG/EX Sweet Cap 350\n\nGeorge McQuillan Ball in Hand PSA 1 Poor-Fair Sovereign 150\n\nGeorge McQuillan Ball in Hand PSA 3 Very Good Sweet Cap 150, Factory 30\n\nGeorge McQuillan Ball in Hand PSA 4 VG/EX Sweet Cap 150, Factory 25\n\nGeorge McQuillan Ball in Hand SGC 50 VG/EX Old Mill\n\nJohn Titus PSA 3 Very Good Sweet Cap 350\n\nJohn Titus PSA 4 VG/EX Old Mill\n\nJohn Titus PSA 3 Very Good Polar Bear\n\nJohn Titus PSA 4 VG/EX Sovereign 350\n\nJohn Titus PSA 5 Excellent Piedmont 350\n\nJohn Titus SGC 30 Good EPDG\n\nJohn Titus SGC 50 VG/EX Sovereign 350",
      "post_time": "20080330T08:29:00-06:00",
      "timestamp": "1206887340"
    }
  ]
}