{
  "id": "143257",
  "forum_id": "13",
  "title": "FS: T205 Mathewson Cycle (SGC 10)",
  "author": "asoriano",
  "reply_count": 0,
  "view_count": 238,
  "created_date": null,
  "last_reply": "20111031T20:06:50-06:00",
  "posts": [
    {
      "post_id": "936157",
      "post_title": "FS: T205 Mathewson Cycle (SGC 10)",
      "post_author_name": "asoriano",
      "post_content": "$2,000 DLVD:\n\n[URL=http://imageshack.us/photo/my-images/822/mattyk.jpg/][IMG]http://img822.imageshack.us/img822/9924/mattyk.jpg[/IMG][/URL]\n\n[URL=http://imageshack.us/photo/my-images/408/matty2n.jpg/][IMG]http://img408.imageshack.us/img408/4472/matty2n.jpg[/IMG][/URL]",
      "post_time": "20111031T20:06:50-06:00",
      "timestamp": "1320113210"
    }
  ]
}