{
  "id": "185057",
  "forum_id": "13",
  "title": "FS S74 Steinfeldt SGC",
  "author": "pete zouras",
  "reply_count": 1,
  "view_count": 264,
  "created_date": null,
  "last_reply": "20141031T14:09:41-06:00",
  "posts": [
    {
      "post_id": "1255936",
      "post_title": "FS S74 Steinfeldt SGC",
      "post_author_name": "pete zouras",
      "post_content": "Bought lot of Turner.  Asking $35 dlvd for S74 Steinfeldt SGC 45 (link below).  Thanks\n\n[url]http://www.b-lauctions.com/LotDetail.aspx?inventoryid=5662[/url]",
      "post_time": "20140318T19:07:12-06:00",
      "timestamp": "1395191232"
    },
    {
      "post_id": "1339421",
      "post_title": "",
      "post_author_name": "pete zouras",
      "post_content": "Bump",
      "post_time": "20141031T14:09:41-06:00",
      "timestamp": "1414786181"
    }
  ]
}