{
  "id": "98370",
  "forum_id": "13",
  "title": "T215 Red Cross Type 1 Magee SOLD",
  "author": "Archive",
  "reply_count": 0,
  "view_count": 327,
  "created_date": null,
  "last_reply": "20080903T19:23:00-06:00",
  "posts": [
    {
      "post_id": "683483",
      "post_title": "T215 Red Cross Type 1 Magee SOLD",
      "post_author_name": "Archive",
      "post_content": "Posted By: Matt\nFor sale, or to use in trade with my cash towards a Wagner or Anson.\n\n[IMG]http://img.auctiva.com/imgdata/6/7/8/8/1/7/webimg/169341873_o.jpg[/IMG][IMG]http://img.auctiva.com/imgdata/6/7/8/8/1/7/webimg/169341897_o.jpg[/IMG]",
      "post_time": "20080903T19:23:00-06:00",
      "timestamp": "1220491380"
    }
  ]
}