{
  "id": "225334",
  "forum_id": "13",
  "title": "WTB/WTTF: Sovereigns",
  "author": "HercDriver",
  "reply_count": 3,
  "view_count": 278,
  "created_date": null,
  "last_reply": "20160729T12:36:24-06:00",
  "posts": [
    {
      "post_id": "1560760",
      "post_title": "WTB/WTTF: Sovereigns",
      "post_author_name": "HercDriver",
      "post_content": "I am looking to buy or trade for the following T205s, with Sovereign backs:\n\nLennox\n[STRIKE]Lobert[/STRIKE] \nB. Lord\n[STRIKE]Lush[/STRIKE]\nMaddox\n\nLet me know what you have!  Also open to trades on any other T205/T206 Sovereigns...\n\nTake Care,\nGeno",
      "post_time": "20160711T13:36:20-06:00",
      "timestamp": "1468265780"
    },
    {
      "post_id": "1561800",
      "post_title": "Lobert in the fold!",
      "post_author_name": "HercDriver",
      "post_content": "OK, Luke came up with Lobert for me, so now looking for Lush in my Top 3.  I need about 25 more T205s to get all the Sovereign backs...let me know!\n\nTake Care,\nGeno",
      "post_time": "20160714T16:43:08-06:00",
      "timestamp": "1468536188"
    },
    {
      "post_id": "1566312",
      "post_title": "Maddox next",
      "post_author_name": "HercDriver",
      "post_content": "Sweet...Lush has found his way to me!!  Only 24 more to find...",
      "post_time": "20160728T08:37:44-06:00",
      "timestamp": "1469716664"
    },
    {
      "post_id": "1566624",
      "post_title": "",
      "post_author_name": "Eggoman",
      "post_content": "Will be listing T205s of Snodgrass and Magee with Sovereign backs soon on B/S/T, but will work with you first, if interested... Send me a PM for details.",
      "post_time": "20160729T12:36:24-06:00",
      "timestamp": "1469817384"
    }
  ]
}