{
  "id": "113309",
  "forum_id": "13",
  "title": "For Sale: 1912 T207 Recruit Little Cigars - Max Carey HOF RC  (SGC 30)",
  "author": "bcbgcbrcb",
  "reply_count": 4,
  "view_count": 828,
  "created_date": null,
  "last_reply": "20090707T15:33:31-06:00",
  "posts": [
    {
      "post_id": "730226",
      "post_title": "For Sale: 1912 T207 Recruit Little Cigars - Max Carey HOF RC  (SGC 30)",
      "post_author_name": "bcbgcbrcb",
      "post_content": "Sold",
      "post_time": "20090616T17:56:14-06:00",
      "timestamp": "1245196574"
    },
    {
      "post_id": "730470",
      "post_title": "PRICE REDUCTION - 1912 Little Recruit Cigarettes T207 Max Carey HOF RC  (SGC 30)",
      "post_author_name": "bcbgcbrcb",
      "post_content": "BUMP due to price reduction.",
      "post_time": "20090617T17:46:43-06:00",
      "timestamp": "1245282403"
    },
    {
      "post_id": "730767",
      "post_title": "FINAL PRICE REDUCTION - 1912 T207 Max Carey HOF RC (SGC 30)",
      "post_author_name": "bcbgcbrcb",
      "post_content": "BUMP due to final price reduction before moving to ebay.",
      "post_time": "20090619T04:39:53-06:00",
      "timestamp": "1245407993"
    },
    {
      "post_id": "734204",
      "post_title": "FINAL PRICE REDUCTION - 1912 T207 Max Carey HOF RC  (SGC 30)",
      "post_author_name": "bcbgcbrcb",
      "post_content": "BUMP due to final price reduction before moving to e-bay.",
      "post_time": "20090706T10:51:12-06:00",
      "timestamp": "1246899072"
    },
    {
      "post_id": "734517",
      "post_title": "E-mail Sent",
      "post_author_name": "T2069bk",
      "post_content": "Just sent an e-mail!",
      "post_time": "20090707T15:33:31-06:00",
      "timestamp": "1247002411"
    }
  ]
}