{
  "id": "355830",
  "forum_id": "13",
  "title": "FS: T205 Schutle (Piedmont 42)",
  "author": "Marckus99",
  "reply_count": 1,
  "view_count": 747,
  "created_date": null,
  "last_reply": "20241206T17:00:41-06:00",
  "posts": [
    {
      "post_id": "2479109",
      "post_title": "FS: T205 Schutle (Piedmont 42)",
      "post_author_name": "Marckus99",
      "post_content": "Tough & presentable $OLD",
      "post_time": "20241205T18:46:14-06:00",
      "timestamp": "1733449574"
    },
    {
      "post_id": "2479312",
      "post_title": "",
      "post_author_name": "benge610",
      "post_content": "Mark,\nI'll take it.\nPM sent.\nBen",
      "post_time": "20241206T17:00:41-06:00",
      "timestamp": "1733529641"
    }
  ]
}