{
  "id": "97957",
  "forum_id": "13",
  "title": "wttf or wtb 1910 T212 Obaks",
  "author": "Archive",
  "reply_count": 0,
  "view_count": 407,
  "created_date": null,
  "last_reply": "20080618T14:57:00-06:00",
  "posts": [
    {
      "post_id": "682251",
      "post_title": "wttf or wtb 1910 T212 Obaks",
      "post_author_name": "Archive",
      "post_content": "Posted By: Andy Cook\nI will buy or trade for the 1910 Obaks listed below to complete my set. I have cards to trade posted at [url]http://members.aol.com/typecard/trade.html[/url] thanks, Andy typecard@aol.com\n\n1910 T212 Wantlist\nAkin, Annies, Baker, Baum, Beall, Berry, Bodie, Browning(Sacramento), Christian, Cooney, Custer, Garrett, Greggs, Hall(Seattle), Johnston, JLewis, Miller(San Francisco) <-- PRIORITY, Miller(Seattle), Netzel, Pennington, Shafer, Shinn, Swander, Thomas, Whalen",
      "post_time": "20080618T14:57:00-06:00",
      "timestamp": "1213822620"
    }
  ]
}